sparp/__init__.py
sparp/sparp.py
sparp-1.10.2.dist-info/licenses/LICENSE.md
sparp-1.10.2.dist-info/METADATA
sparp-1.10.2.dist-info/WHEEL
sparp-1.10.2.dist-info/top_level.txt
sparp-1.10.2.dist-info/RECORD
