Metadata-Version: 2.4
Name: sparp
Version: 1.10.2
Summary: Simple Parallel Asynchronous Requests for Python
Author: Frederik Bode
License-Expression: MIT
Requires-Python: >=3.13
License-File: LICENSE.md
Requires-Dist: aiohttp~=3.13.2
Dynamic: license-file
